{
  "thread": {
    "uuid": "07e01b34abfef20f50fb1415b987e8307794c55a",
    "url": "https://expresso.pt/semanario/ideias/2024-12-05-o-treino-musical-provoca-alteracoes-no-cerebro-das-criancas-a9fc8b89",
    "site_full": "expresso.pt",
    "site": "expresso.pt",
    "site_section": "https://expresso.pt/semanario/primeiro/o-futuro-do-futuro",
    "site_categories": [
      "media",
      "top_news_pt",
      "top_news"
    ],
    "section_title": "O Futuro do Futuro - Expresso",
    "title": "“O treino musical provoca alterações no cérebro das crianças”",
    "title_full": "“O treino musical provoca alterações no cérebro das crianças”",
    "published": "2024-12-05T23:57:00.000+02:00",
    "replies_count": 0,
    "participants_count": 1,
    "site_type": "news",
    "country": "PT",
    "main_image": "https://images.impresa.pt/expresso/2024-12-05-assal_habibi_piano_3_t-_idp.jpg-05d2f563/1.91x1?wm=true&amp;outputFormat=jpeg",
    "performance_score": 0,
    "domain_rank": 19057,
    "domain_rank_updated": "2024-12-02T23:00:00.000+02:00",
    "social": {
      "facebook": {
        "likes": 0,
        "comments": 0,
        "shares": 0
      },
      "vk": {
        "shares": 0
      }
    }
  },
  "uuid": "07e01b34abfef20f50fb1415b987e8307794c55a",
  "url": "https://expresso.pt/semanario/ideias/2024-12-05-o-treino-musical-provoca-alteracoes-no-cerebro-das-criancas-a9fc8b89",
  "ord_in_thread": 0,
  "parent_url": null,
  "author": "Joana Pereira Bastos",
  "published": "2024-12-05T23:57:00.000+02:00",
  "title": "“O treino musical provoca alterações no cérebro das crianças”",
  "text": "Assal Habibi, Investigadora do Brain and Creativity Institute, da Universidade do Sul da Califórnia, explica de que forma o ensino da música promove o sucesso escolar, fortalece competências como a atenção, a memória e a capacidade de planeamento e melhora a regulação das emoções\nNos últimos 12 anos, o Brain and Creativity Institute, da Universidade do Sul da Califórnia, liderado pelo neurocientista português António Damásio, conduziu o maior estudo longitudinal sobre o impacto da formação musical no desenvolvimento cognitivo e socioemocional das crianças. Em entrevista ao Expresso, a investigadora Assal Habibi, que coordenou a pesquisa, explica de que forma o ensino da música promove o sucesso escolar, fortalece competências como a atenção, a memória e a capacidade de planeamento e melhora a regulação das emoções e a interação com os outros. Para a especialista, os resultados desta investigação — que vão ser apresentados pela primeira vez em Portugal esta sexta-feira, no congresso do centro clínico PIN, em Carcavelos — devem levar a uma mudança dos currículos escolares.\nTem dúvidas, sugestões ou críticas? Envie-me um e-mail: [JBastos@expresso.impresa.pt](mailto:JBastos@expresso.impresa.pt)",
  "highlightText": "",
  "highlightTitle": "",
  "highlightThreadTitle": "",
  "language": "portuguese",
  "sentiment": "positive",
  "categories": [
    "Education",
    "Health"
  ],
  "topics": null,
  "ai_allow": true,
  "has_canonical": false,
  "webz_reporter": false,
  "external_links": [],
  "external_images": [],
  "entities": {
    "persons": [],
    "organizations": [],
    "locations": []
  },
  "syndication": {
    "syndicated": null,
    "syndicate_id": null,
    "first_syndicated": false
  },
  "rating": null,
  "crawled": "2024-12-06T02:17:04.791+02:00",
  "updated": "2024-12-06T02:17:04.791+02:00"
}