{
  "thread": {
    "uuid": "6b138f2ce76df008079a5e22d95db367f1f9e3d9",
    "url": "https://www.foxweather.com/watch/play-79956f8600016ac",
    "site_full": "www.foxweather.com",
    "site": "foxweather.com",
    "site_section": "https://www.foxweather.com/",
    "site_categories": [],
    "section_title": "Breaking Weather News | FOX Weather Home of America&#x27;s Weather Team",
    "title": "Severe weather to threaten hard-hit communities in the South this weekend | Latest Weather Clips | FOX Weather",
    "title_full": "Severe weather to threaten hard-hit communities in the South this weekend | Latest Weather Clips | FOX Weather",
    "published": "2025-01-03T13:26:00.000+02:00",
    "replies_count": 0,
    "participants_count": 1,
    "site_type": "news",
    "country": "US",
    "main_image": "https://images.foxweather.com/static-media.fox.com/ms/stg1/weather/992/558/play-79956f8600016ac--36889051503.jpg?ve=1&amp;tl=1",
    "performance_score": 0,
    "domain_rank": 11604,
    "domain_rank_updated": "2024-12-30T23:00:00.000+02:00",
    "social": {
      "facebook": {
        "likes": 0,
        "comments": 0,
        "shares": 0
      },
      "vk": {
        "shares": 0
      }
    }
  },
  "uuid": "6b138f2ce76df008079a5e22d95db367f1f9e3d9",
  "url": "https://www.foxweather.com/watch/play-79956f8600016ac",
  "ord_in_thread": 0,
  "parent_url": null,
  "author": "@foxweather",
  "published": "2025-01-03T13:26:00.000+02:00",
  "title": "Severe weather to threaten hard-hit communities in the South this weekend | Latest Weather Clips | FOX Weather",
  "text": "A little more than a week after a tornado outbreak ripped through parts of Texas, Louisiana and Mississippi, those same areas find themselves under the threat for severe storms once again this weekend.",
  "highlightText": "",
  "highlightTitle": "",
  "highlightThreadTitle": "",
  "language": "english",
  "sentiment": "negative",
  "categories": [
    "Weather",
    "Disaster and Accident",
    "Social Issue"
  ],
  "topics": [
    "Weather->weather warning",
    "Disaster and Accident->natural disaster",
    "Social Issue->communities",
    "Social Issue->social problem",
    "Social Issue->charity"
  ],
  "ai_allow": true,
  "has_canonical": false,
  "webz_reporter": false,
  "external_links": [],
  "external_images": [],
  "entities": {
    "persons": [],
    "organizations": [],
    "locations": []
  },
  "syndication": {
    "syndicated": false,
    "syndicate_id": null,
    "first_syndicated": false
  },
  "rating": null,
  "crawled": "2025-01-03T15:28:27.739+02:00",
  "updated": "2025-01-03T15:28:27.739+02:00"
}