{
  "thread": {
    "uuid": "f37ffebe13c912de2e4adf23e021d5a7436c4cc4",
    "url": "https://flipboard.com/article/the-ghost-busting-girl-detective-who-awed-houdini/f-8742fe433e%2Fatlasobscura.com",
    "site_full": "flipboard.com",
    "site": "flipboard.com",
    "site_section": "https://flipboard.com/topic/spirituality",
    "site_categories": [
      "family_and_parenting",
      "eldercare"
    ],
    "section_title": "Spirituality Articles, News, and Stories | Flipboard",
    "title": "The Ghost-Busting 'Girl Detective' Who Awed Houdini | Flipboard",
    "title_full": "The Ghost-Busting 'Girl Detective' Who Awed Houdini | Flipboard",
    "published": "2024-03-14T02:00:00.000+02:00",
    "replies_count": 0,
    "participants_count": 1,
    "site_type": "news",
    "country": "US",
    "main_image": "https://ic-cdn.flipboard.com/atlasobscura.com/cf6a6d203f21adb4ce6fb5b21b5ad048de09e8ec/_medium.png",
    "performance_score": 0,
    "domain_rank": 1226,
    "domain_rank_updated": "2024-03-12T12:10:46.000+02:00",
    "reach": null,
    "social": {
      "facebook": {
        "likes": 0,
        "comments": 0,
        "shares": 0
      },
      "gplus": {
        "shares": 0
      },
      "pinterest": {
        "shares": 0
      },
      "linkedin": {
        "shares": 0
      },
      "stumbledupon": {
        "shares": 0
      },
      "vk": {
        "shares": 0
      }
    }
  },
  "uuid": "f37ffebe13c912de2e4adf23e021d5a7436c4cc4",
  "url": "https://flipboard.com/article/the-ghost-busting-girl-detective-who-awed-houdini/f-8742fe433e%2Fatlasobscura.com",
  "ord_in_thread": 0,
  "parent_url": null,
  "author": "Atlas Obscura - Nina Strochlic",
  "published": "2024-03-14T02:00:00.000+02:00",
  "title": "The Ghost-Busting 'Girl Detective' Who Awed Houdini | Flipboard",
  "text": "The Ghost-Busting 'Girl Detective' Who Awed Houdini As an undercover investigator, Rose Mackenberg unmasked hundreds of America’s fake psychics. Rose Mackenberg started as a believer: In the early 20th … More stories from [Spirituality](/topic/spirituality) More stories from [Magic](/topic/magictrick) [Former Patriots QB questions NFL team breaking the bank on ‘extremely alarming’ player](/topic/magictrick/former-patriots-qb-questions-nfl-team-breaking-the-bank-on-extremely-alarming-/a-8_1Zt23CRpGQ1lPIlp8HBQ%3Aa%3A2878678510-8987ce5a04%2Fmasslive.com) Cam Newton wants to know who Kirk Cousins’ agent is -- because apparently they’re a magician. The former New England Patriots quarterback reacted to … [Your guide to fun this weekend on Staten Island: Celebrate St. Patrick’s Day and more](/topic/magictrick/your-guide-to-fun-this-weekend-on-staten-island-celebrate-st-patrick-s-day-and/a-IYrnqdL4T7i550xssPkJ7Q%3Aa%3A2830815725-db7ed13710%2Fsilive.com) STATEN ISLAND, N.Y. - Staten Island is brimming with diverse activities in arts, culture and beyond.SaturdayMasters of Illusion / March 16, 7 … [Watch Shohei Ohtani's Reaction to Insane Magic Trick in Dodgers Clubhouse](/topic/magictrick/watch-shohei-ohtani-s-reaction-to-insane-magic-trick-in-dodgers-clubhouse/a-yS8XPhD4TiGXQqt6EVA0sA%3Aa%3A3654265270-27e772822e%2Fsi.com) Even the great Ohtani was amazed by this magic trick. Spring training at Camelback Ranch for the Los Angeles Dodgers has come and gone, and what an … Join the flipboard community Discover, collect, and share stories for all your interests [Sign up](/signup) More stories from [Spiritualism](/topic/spiritualism) [Jam Dass, 'Love, Jam, Remember'](/topic/spiritualism/jam-dass-love-jam-remember/a-KHLDqRuLTuGNCh5o7sI43w%3Aa%3A3333583062-7e2d9ad0ab%2Fsevendaysvt.com) (Self released, CD, digital) I'm going to be honest: I thought I was being pranked when I first hit play on Jam Dass' debut record, Love, Jam, … [One thing all education ministers under Nehru aimed to do—make Indians doubt ancient values](/topic/spiritualism/one-thing-all-education-ministers-under-nehru-aimed-to-do-make-indians-doubt-anc/a-hxc6dYPYTP6v1kERGBy_kQ%3Aa%3A2795223453-b4728a96dd%2Ftheprint.in) In 'Modian Consensus', Swadesh Singh talks about how the Nehruvian Consensus demolished the ideas of the Civilisational Consensus that had …",
  "highlightText": "",
  "highlightTitle": "",
  "highlightThreadTitle": "",
  "language": "english",
  "sentiment": "positive",
  "categories": [
    "Human Interest"
  ],
  "external_links": [],
  "external_images": [],
  "entities": {
    "persons": [
      {
        "name": "rose mackenberg",
        "sentiment": "negative"
      },
      {
        "name": "cam newton",
        "sentiment": "none"
      }
    ],
    "organizations": [
      {
        "name": "nfl",
        "sentiment": "none"
      },
      {
        "name": "new england patriots",
        "sentiment": "none"
      }
    ],
    "locations": [
      {
        "name": "n.y.",
        "sentiment": "none"
      },
      {
        "name": "staten island",
        "sentiment": "none"
      },
      {
        "name": "staten island",
        "sentiment": "none"
      },
      {
        "name": "america",
        "sentiment": "none"
      }
    ]
  },
  "rating": null,
  "crawled": "2024-03-15T00:07:30.470+02:00",
  "updated": "2024-03-15T00:07:30.470+02:00"
}