{
  "thread": {
    "uuid": "bb35ba04bc76f3d25d984d9198b0842772309fe7",
    "url": "https://exa.unicen.edu.ar/becas-de-grado-y-posgrado-del-gobierno-de-hungria",
    "site_full": "exa.unicen.edu.ar",
    "site": "unicen.edu.ar",
    "site_section": "https://exa.unicen.edu.ar/feed/",
    "site_categories": [],
    "section_title": "Facultad de Ciencias Exactas",
    "title": "Becas de grado y posgrado del Gobierno de Hungría",
    "title_full": "Becas de grado y posgrado del Gobierno de Hungría",
    "published": "2024-12-05T22:12:00.000+02:00",
    "replies_count": 0,
    "participants_count": 1,
    "site_type": "news",
    "country": "AR",
    "main_image": "",
    "performance_score": 0,
    "domain_rank": 35794,
    "domain_rank_updated": "2024-12-02T23:00:00.000+02:00",
    "social": {
      "facebook": {
        "likes": 0,
        "comments": 0,
        "shares": 0
      },
      "vk": {
        "shares": 0
      }
    }
  },
  "uuid": "bb35ba04bc76f3d25d984d9198b0842772309fe7",
  "url": "https://exa.unicen.edu.ar/becas-de-grado-y-posgrado-del-gobierno-de-hungria",
  "ord_in_thread": 0,
  "parent_url": null,
  "author": "acarbajo",
  "published": "2024-12-05T22:12:00.000+02:00",
  "title": "Becas de grado y posgrado del Gobierno de Hungría",
  "text": "[vc_row][vc_column width=»2/3″][vc_column_text css=»»]\nEl programa de becas Stipendium Hungaricum fue lanzado en 2013 por el gobierno húngaro. El objetivo es apoyar la internacionalización de la Educación Superior húngara y fortalecer las relaciones internacionales de la comunidad académica y de investigación húngara. El programa también tiene como objetivo fomentar el apego personal y profesional de los estudiantes extranjeros con Hungría y contribuir a la promoción de la cultura y del idioma húngaro en el mundo. Dirigido a: Estudiantes de grado y posgrado (maestria, doctorado), graduados/as. Beneficios Grado y maestría: – Educación gratuita: exención del pago de tasas de matrícula. – Estipendio mensual: importe mensual de 43.700 HUF (aproximadamente 2.110 EUR) hasta la finalización de los estudios. -Alojamiento – Plaza en residencia gratuita (según la capacidad institucional) o una contribución de 40.000 HUF/mes (aproximadamente 100 EUR) para los gastos de alojamiento durante toda la beca. – Seguro médico. – Aclaración: no cubre completamente todos los costos de vida y los estudiantes deben agregar sus propios recursos financieros para cubrir todos los gastos de vida en Hungría. Doctorado – Educación gratuita: exención del pago de tasas de matrícula. – Beca mensual: nivel de doctorado: según la legislación húngara vigente, el importe mensual de la beca es de 140.000 HUF (aproximadamente 1.350 EUR) para la primera fase de la educación (4 semestres) y 180.000 HUF (aproximadamente 450 EUR) para la segunda fase (4 semestres), durante 12 meses al año, hasta la finalización de los estudios. – Contribución al alojamiento: plaza gratuita en la residencia (según la capacidad institucional) o una contribución de 40.000 HUF/mes (aproximadamente 100 EUR) para los costes de alojamiento durante toda la duración del período de la beca. – Seguro médico. Área de interés: Ciencias Puras y Aplicadas; Computación, Matemáticas y Ciencias de la Información; Ingeniería y Tecnología. Cierre convocatoria: 15/01/2015 Para conocer más de estas propuestas, escribir a rrii@exa.unicen.edu.ar o acercarse a la Secretaría de Investigación y Postgrado de la FCEx, de lunes a viernes de 9 a 14 hs. [/vc_column_text][/vc_column][vc_column width=»1/3″ css=».vc_custom_1643990987242{border-top-width: 1px !important;border-right-width: 1px !important;border-bottom-width: 1px !important;border-left-width: 1px !important;border-left-color: #00cccc !important;border-left-style: solid !important;border-right-color: #00cccc !important;border-right-style: solid !important;border-top-color: #00cccc !important;border-top-style: solid !important;border-bottom-color: #00cccc !important;border-bottom-style: solid !important;}»][vc_column_text css=»»]\nDocumentación Más información Becas de Grado\nMás información Becas de posgrado\nBases y condiciones Becas de Grado y Maestría\nBases y condiciones Becas de Doctorado\n[/vc_column_text][/vc_column][/vc_row]",
  "highlightText": "",
  "highlightTitle": "",
  "highlightThreadTitle": "",
  "language": "spanish",
  "sentiment": "positive",
  "categories": [
    "Education"
  ],
  "topics": null,
  "ai_allow": true,
  "has_canonical": false,
  "webz_reporter": false,
  "external_links": [],
  "external_images": [],
  "entities": {
    "persons": [],
    "organizations": [
      {
        "name": "Gobierno",
        "sentiment": "neutral"
      }
    ],
    "locations": []
  },
  "syndication": {
    "syndicated": null,
    "syndicate_id": null,
    "first_syndicated": false
  },
  "rating": null,
  "crawled": "2024-12-06T00:19:02.216+02:00",
  "updated": "2024-12-06T03:06:34.104+02:00"
}