{
  "thread": {
    "uuid": "16b2867bccd6c89c3a25b01086366c23e85011a3",
    "url": "https://flipboard.com/topic/tualatinrivervalley/oregon-caves-chateau-named-one-of-nation-s-most-endangered-historic-places---phi/f-9c0f8124fa%2Fphilomathnews.com",
    "site_full": "flipboard.com",
    "site": "flipboard.com",
    "site_section": "https://flipboard.com/topic/tualatinrivervalley",
    "site_categories": [
      "family_and_parenting",
      "eldercare"
    ],
    "section_title": "Discover More in Tualatin River Valley on Flipboard",
    "site_title": "Flipboard: Your Social Magazine",
    "title": "Oregon Caves chateau named one of nation's most endangered historic places - Philomath News | Flipboard",
    "title_full": "Oregon Caves chateau named one of nation's most endangered historic places - Philomath News | Flipboard",
    "published": "2025-05-08T01:33:00.000+03:00",
    "replies_count": 0,
    "participants_count": 1,
    "site_type": "news",
    "country": "US",
    "main_image": "https://philomathnews.com/wp-content/uploads/2025/05/050725-OregonCavesChateau_BeforeClosure.jpg",
    "performance_score": 0,
    "domain_rank": 1243,
    "domain_rank_updated": "2025-05-06T00:00:00.000+03:00",
    "licensing_agency": [],
    "social": {
      "facebook": {
        "likes": 0,
        "comments": 0,
        "shares": 0
      },
      "vk": {
        "shares": 0
      }
    }
  },
  "uuid": "16b2867bccd6c89c3a25b01086366c23e85011a3",
  "url": "https://flipboard.com/topic/tualatinrivervalley/oregon-caves-chateau-named-one-of-nation-s-most-endangered-historic-places---phi/f-9c0f8124fa%2Fphilomathnews.com",
  "ord_in_thread": 0,
  "author": "philomathnews.com - Julia Shumway, Oregon Capital Chronicle",
  "published": "2025-05-08T01:33:00.000+03:00",
  "title": "Oregon Caves chateau named one of nation's most endangered historic places - Philomath News | Flipboard",
  "text": "Oregon Caves chateau named one of nation’s most endangered historic places - Philomath News The Depression-era chateau at the Oregon Caves National Monument and Preserve, closed since 2018 for rehabilitation work, is one of the nation’s most …\nphilomathnews.com - Julia Shumway, Oregon Capital Chronicle • 2h",
  "highlightText": "",
  "highlightTitle": "",
  "highlightThreadTitle": "",
  "language": "english",
  "sentiment": "negative",
  "categories": [
    "Environment",
    "Social Issue",
    "Human Interest"
  ],
  "topics": [
    "Environment->endangered species",
    "Environment->natural resources",
    "Environment->conservation",
    "Social Issue->communities",
    "Social Issue->indigenous people",
    "Human Interest->record and achievement"
  ],
  "ai_allow": true,
  "has_canonical": false,
  "breaking": false,
  "webz_reporter": false,
  "external_links": [],
  "entities": {
    "persons": [
      {
        "name": "Julia Shumway",
        "sentiment": "none"
      }
    ],
    "locations": [],
    "organizations": [
      {
        "name": "Oregon Capital Chronicle",
        "sentiment": "none",
        "tickers": []
      }
    ]
  },
  "syndication": {
    "syndicated": false,
    "syndicate_id": null,
    "first_syndicated": false
  },
  "trust": {
    "categories": [],
    "bias": null,
    "source": {
      "type": null,
      "city": null,
      "state": null,
      "country": null,
      "domain_type": null,
      "agency": null,
      "organization_name": null
    }
  },
  "rating": null,
  "crawled": "2025-05-08T04:27:06.095+03:00",
  "updated": "2025-05-08T01:34:47.000+00:00"
}