{
  "thread": {
    "uuid": "0330357d08072b4c871f8c7cccaa6dd821a87dcb",
    "url": "https://acento.com.do/opinion/claves-para-cuidar-tu-reputacion-digital-9551978.html",
    "site_full": "acento.com.do",
    "site": "acento.com.do",
    "site_section": "https://acento.com.do",
    "site_categories": [
      "media"
    ],
    "section_title": "Acento | Últimas noticias de Santo Domingo, República Dominicana y el mundo",
    "site_title": "Acento | Últimas noticias de Santo Domingo, República Dominicana y el mundo",
    "title": "Claves para cuidar tu reputación digital",
    "title_full": "Claves para cuidar tu reputación digital",
    "published": "2025-09-18T06:03:00.000+03:00",
    "replies_count": 0,
    "participants_count": 1,
    "site_type": "news",
    "country": "DO",
    "main_image": "https://media.acento.com.do/media/storage02/uploads/2020/06/Nestor-Estevez.png",
    "performance_score": 0,
    "domain_rank": 195909,
    "domain_rank_updated": "2025-09-16T00:00:00.000+03:00",
    "licensing_agency": [],
    "social": {
      "facebook": {
        "likes": 0,
        "comments": 0,
        "shares": 0
      },
      "vk": {
        "shares": 0
      }
    }
  },
  "uuid": "0330357d08072b4c871f8c7cccaa6dd821a87dcb",
  "url": "https://acento.com.do/opinion/claves-para-cuidar-tu-reputacion-digital-9551978.html",
  "ord_in_thread": 0,
  "author": "Frontaly",
  "published": "2025-09-18T06:03:00.000+03:00",
  "title": "Claves para cuidar tu reputación digital",
  "text": "Recientemente he publicado sobre reputación, sobre esa huella o sello que dejamos en los demás y que termina condicionando nuestras relaciones. Así vimos cómo los hábitos cotidianos terminan creando un “sello” personal: una especie de marca que otros perciben de nosotros.\nExplicamos sobre gente que termina ganándose motes como “el negativo”. También vimos que el asunto no se queda ahí, sino que así recuerdan los demás a esa gente y que como tal la tratan.\nPor fortuna, también vimos que quienes por sus hábitos y acciones dejan huellas positivas logran fama de ser personas confiables, solidarias o cualquier otra etiqueta que se correspondan con sus actuaciones habituales. Referimos que las huellas, positivas o negativas, se forman e inciden en la familia, en la comunidad o en el trabajo y en otros muy diversos ámbitos de la sociedad.\nPero siendo las redes sociales esa especie de “arena pública”, como la llaman algunos especialistas, y que han llegado a lograr omnipresencia en nuestras vidas, es muy válido preguntarse: ¿qué ocurre con nuestras huellas en redes sociales?\nSencillamente, lo que publicamos nos define. Y así ocurre porque cada publicación en redes sociales es un espejo que amplifica nuestra marca personal. En redes como Facebook, Instagram o X (antes Twitter), lo que compartimos deja huellas más fuertes que en la conversación cara a cara.\nSi alguien publica constantemente noticias tristes, quejas o burlas, pronto será visto como “el pesimista” o “el amargado digital”. Aunque en su vida real sea diferente, la percepción en el mundo virtual termina pesando. Así es como una simple mirada sirve para identificar a quien protesta por todo, a quien vive de denostar, en fin, a cada quien según lo que publica.\nPor el contrario, quien comparte contenido útil, reflexiones equilibradas o momentos positivos de la vida cotidiana suele ser recordado como alguien que inspira confianza o genera buen ánimo. Es lo que algunos especialistas llaman marca o huella digital: la versión pública de nuestro sello personal en internet.\nEn uno y en otro caso, aunque publiquen pensando en que se están dirigiendo a su “blanco de público” y hasta con el convencimiento de que “se la están comiendo”, lo real es que, dependiendo de quien vea sus mensajes, están diciendo mucho sobre su propia persona.\nA cada quien lo suyo\nQuien siempre comparte quejas políticas, aunque tenga razón en algunos planteamientos, con el tiempo la gente lo identifica como “el que todo lo critica” y termina perdiendo. Mientras, quien llena sus redes de frases motivadoras y gestos solidarios también “cosecha lo suyo”: se convierte en referente de esperanza para sus contactos, aunque tenga sus propios problemas.\nLa diferencia principal con las redes es que lo que publicamos queda registrado. Una conversación cara a cara se olvida con el tiempo; un post o un tuit puede ser recordado años después. Eso hace que el sello digital sea aún más fuerte. Incluso, aunque borremos, alguien pudo haberlo guardado, y lo puede volver a publicar.\nPor eso, antes de publicar, conviene preguntarse: ¿esto aporta algo? ¿A quién? ¿Quiero que me recuerden por este tipo de mensajes? ¿Me suma o me resta como persona?\nClaves fundamentales\nAlgunas claves sencillas y muy prácticas pueden ayudarnos a bien gestionar nuestra reputación digital:\n1.- Ser selectivos. No todo lo que pensamos o nos llega merece ser publicado. Elegir bien lo que compartimos es cuidar nuestro sello.\n2.- Equilibrar. Está bien denunciar problemas, pero conviene acompañarlos con propuestas, datos o ejemplos positivos.\n3.- Mostrar humanidad. No se trata de parecer perfectos, sino de reflejar un balance: logros, aprendizajes, errores y también gratitud.\n4.- Pensar en el futuro. Lo que publicamos hoy puede influir en oportunidades laborales, relaciones o proyectos mañana.\n5.- Revisar el historial. De vez en cuando conviene mirar lo que hemos compartido, y borrar lo que ya no refleja quiénes somos.\nRecuerda: tanto en la vida diaria como en las redes sociales, nuestro sello se construye con lo que repetimos. Lo que decimos y hacemos, incluso sin proponérnoslo, se convierte en la huella por la que otros nos recuerdan. Así se construye nuestra reputación digital.\nConcluyo preguntando: ¿qué quieres que la gente piense cuando vea tu nombre en una publicación digital?",
  "highlightText": "",
  "highlightTitle": "",
  "highlightThreadTitle": "",
  "language": "spanish",
  "sentiment": "positive",
  "categories": [
    "Lifestyle and Leisure",
    "Human Interest",
    "Education"
  ],
  "topics": [
    "Lifestyle and Leisure->wellness",
    "Lifestyle and Leisure->mental wellbeing",
    "Lifestyle and Leisure->lifestyle",
    "Education->social learning"
  ],
  "ai_allow": true,
  "has_canonical": false,
  "breaking": null,
  "webz_reporter": false,
  "external_links": [],
  "external_images": [],
  "internal_images": [],
  "entities": {
    "persons": [],
    "locations": [],
    "organizations": []
  },
  "syndication": {
    "syndicated": null,
    "syndicate_id": null,
    "first_syndicated": false
  },
  "trust": {
    "categories": [],
    "top_news": [],
    "bias": null,
    "source": {
      "type": null,
      "city": null,
      "state": null,
      "country": null,
      "domain_type": null,
      "agency": null,
      "organization_name": null
    }
  },
  "rating": null,
  "crawled": "2025-09-18T07:40:19.162+03:00",
  "updated": "2025-09-18T07:45:50.000+03:00"
}